1_RTL/4_COMB_LOGIC/3_DECODER/bcd_to_7seg.v
module bcd_to_7seg(
	//port list
	i_bcd		,
	o_seg		,
);
//port declaration
input	[3:0]	i_bcd	;
output	[6:0]	o_seg	;

//modeling
reg	[6:0]	o_seg	;
always @(i_bcd) begin
	case(i_bcd)
		4'b0000 : o_seg = 7'b1111110; // 0
		4'b0001 : o_seg = 7'b0110000; // 1
		4'b0010 : o_seg = 7'b1101101; // 2
		4'b0011 : o_seg = 7'b1111001; // 3
		4'b0100 : o_seg = 7'b0110011; // 4
		4'b0101 : o_seg = 7'b1011011; // 5
		4'b0110 : o_seg = 7'b1011111; // 6
		4'b0111 : o_seg = 7'b1110000; // 7
		4'b1000 : o_seg = 7'b1111111; // 8
		4'b1001 : o_seg = 7'b1111011; // 9
		default : o_seg = 7'b0000000; // disabled
	endcase
end
endmodule

1_RTL/4_COMB_LOGIC/3_DECODER/tb_bcd_to_7seg.v
module tb_bcd_to_7seg;
//stimulus siganl
reg	[3:0]	i_bcd	;
//monitor signal
wire 	[6:0]	o_seg	;

//DUT instantiation
bcd_to_7seg dut(
	.i_bcd(i_bcd)	,
	.o_seg(o_seg)	
);

//Dumpfile gen
initial begin
	$dumpfile("./bcd_to_7seg.vcd"	);
	$dumpvars(0, tb_bcd_to_7seg	);
end

//apply stimulus
initial begin
	//monitoring
	$monitor("Time=%02t | i_bcd Input=%b | Seven Segment Output=%b", $time, i_bcd, o_seg);

	//apply stimulus
	 i_bcd = 4'b0000; #10; 
	 i_bcd = 4'b0001; #10; 
	 i_bcd = 4'b0010; #10; 
	 i_bcd = 4'b0011; #10; 
	 i_bcd = 4'b0100; #10; 
	 i_bcd = 4'b0101; #10; 
	 i_bcd = 4'b0110; #10; 
	 i_bcd = 4'b0111; #10; 
	 i_bcd = 4'b1000; #10; 
	 i_bcd = 4'b1001; #10; 
	 $finish;
end
endmodule

1_RTL/4_COMB_LOGIC/3_DECODER/bcd_to_7seg.vcd
$date
    Jul  1, 2026  19:13:10
$end
$version
    TOOL:	xmsim(64)	22.03-s012
$end
$timescale
    1 ns
$end

$scope module tb_bcd_to_7seg $end
$var reg       4 !    i_bcd [3:0] $end
$var wire      7 "    o_seg [6:0] $end

$scope module dut $end
$var wire      4 #    i_bcd [3:0] $end
$var reg       7 $    o_seg [6:0] $end
$upscope $end

$upscope $end

$enddefinitions $end
$dumpvars
b0 !
b1111110 "
b0 #
b1111110 $
$end
#10
b1 !
b1 #
b110000 $
b110000 "
#20
b10 !
b10 #
b1101101 $
b1101101 "
#30
b11 !
b11 #
b1111001 $
b1111001 "
#40
b100 !
b100 #
b110011 $
b110011 "
#50
b101 !
b101 #
b1011011 $
b1011011 "
#60
b110 !
b110 #
b1011111 $
b1011111 "
#70
b111 !
b111 #
b1110000 $
b1110000 "
#80
b1000 !
b1000 #
b1111111 $
b1111111 "
#90
b1001 !
b1001 #
b1111011 $
b1111011 "
