1_RTL/5_SEQ_LOGIC/2_REGISTER/register.v
`timescale 1ns/1ps

module register(
	//port list
	rst_n		,
	clk		,
	i_in1		,
	i_in2		,
	o_out1		,
	o_out2
);
//port declaration
input		rst_n		;
input		clk		;
input		i_in1		;
input	[3:0]	i_in2		;
output		o_out1		;
output	[3:0]	o_out2		;

//behavioral modeling : 1-bit register
reg	o_out1					;	
always @(posedge clk or negedge rst_n)
begin
	if(~rst_n) 	o_out1 <= 1'b0		;
	else 		o_out1 <= i_in1		;
end

//behavioral modeling : 4-bit register
reg	[3:0]	o_out2				;
always @(posedge clk or negedge rst_n)
begin
	if(~rst_n)	o_out2 <= 4'b0		;
	else		o_out2 <= i_in2		;
end

endmodule

1_RTL/5_SEQ_LOGIC/2_REGISTER/tb_register.v
`timescale 1ns/1ps

module tb_register;

//stimulus sig
reg		rst_n		;
reg		clk		;
reg		i_in1		;
reg	[3:0]	i_in2		;
//monitor sig
wire		o_out1		;
wire	[3:0]	o_out2		;

//DUT instantiation
register dut(
	.rst_n		(rst_n	)	,
	.clk		(clk	)	,
	.i_in1		(i_in1	)	,
	.i_in2		(i_in2	)	,
	.o_out1		(o_out1	)	,
	.o_out2		(o_out2	)		
);
//dumpfile gen
initial begin
	$dumpfile("./register.vcd"	)		;
	$dumpvars(0, tb_register	)		;
end


//stimulus scenario
//clkgen
always #5 clk = ~clk		;

//init
initial begin
	rst_n	= 1'b0		; // active low rst
	clk	= 1'b0		;
	i_in1	= 1'b0		;
	i_in2	= 4'b0000	;	

	// rst release
	#1000 rst_n = 1'b1	;
	
	#200 i_in1 = 1'b1	;
	
	#100 i_in2 = 4'b1010	;


	//rst enable
	#500 rst_n = 1'b0	;

	#200 i_in1 = 1'b0	;
	     i_in2 = 4'd0	;

	#300 i_in1 = 1'b1	;
	     i_in2 = 4'b1111	;

	#100 rst_n = 1'b1	;

	#200 $finish;
end


endmodule

1_RTL/5_SEQ_LOGIC/2_REGISTER/register.vcd
$date
    Jul  2, 2026  01:53:49
$end
$version
    TOOL:	xmsim(64)	22.03-s012
$end
$timescale
    1 ps
$end

$scope module tb_register $end
$var reg       1 !    rst_n $end
$var reg       1 "    clk $end
$var reg       1 #    i_in1 $end
$var reg       4 $    i_in2 [3:0] $end
$var wire      1 %    o_out1  $end
$var wire      4 &    o_out2 [3:0] $end

$scope module dut $end
$var wire      1 '    rst_n  $end
$var wire      1 (    clk  $end
$var wire      1 )    i_in1  $end
$var wire      4 *    i_in2 [3:0] $end
$var reg       1 +    o_out1 $end
$var reg       4 ,    o_out2 [3:0] $end
$upscope $end

$upscope $end

$enddefinitions $end
$dumpvars
0!
0"
0#
b0 $
0%
b0 &
0'
0(
0)
b0 *
0+
b0 ,
$end
#5000
1"
1(
#10000
0"
0(
#15000
1"
1(
#20000
0"
0(
#25000
1"
1(
#30000
0"
0(
#35000
1"
1(
#40000
0"
0(
#45000
1"
1(
#50000
0"
0(
#55000
1"
1(
#60000
0"
0(
#65000
1"
1(
#70000
0"
0(
#75000
1"
1(
#80000
0"
0(
#85000
1"
1(
#90000
0"
0(
#95000
1"
1(
#100000
0"
0(
#105000
1"
1(
#110000
0"
0(
#115000
1"
1(
#120000
0"
0(
#125000
1"
1(
#130000
0"
0(
#135000
1"
1(
#140000
0"
0(
#145000
1"
1(
#150000
0"
0(
#155000
1"
1(
#160000
0"
0(
#165000
1"
1(
#170000
0"
0(
#175000
1"
1(
#180000
0"
0(
#185000
1"
1(
#190000
0"
0(
#195000
1"
1(
#200000
0"
0(
#205000
1"
1(
#210000
0"
0(
#215000
1"
1(
#220000
0"
0(
#225000
1"
1(
#230000
0"
0(
#235000
1"
1(
#240000
0"
0(
#245000
1"
1(
#250000
0"
0(
#255000
1"
1(
#260000
0"
0(
#265000
1"
1(
#270000
0"
0(
#275000
1"
1(
#280000
0"
0(
#285000
1"
1(
#290000
0"
0(
#295000
1"
1(
#300000
0"
0(
#305000
1"
1(
#310000
0"
0(
#315000
1"
1(
#320000
0"
0(
#325000
1"
1(
#330000
0"
0(
#335000
1"
1(
#340000
0"
0(
#345000
1"
1(
#350000
0"
0(
#355000
1"
1(
#360000
0"
0(
#365000
1"
1(
#370000
0"
0(
#375000
1"
1(
#380000
0"
0(
#385000
1"
1(
#390000
0"
0(
#395000
1"
1(
#400000
0"
0(
#405000
1"
1(
#410000
0"
0(
#415000
1"
1(
#420000
0"
0(
#425000
1"
1(
#430000
0"
0(
#435000
1"
1(
#440000
0"
0(
#445000
1"
1(
#450000
0"
0(
#455000
1"
1(
#460000
0"
0(
#465000
1"
1(
#470000
0"
0(
#475000
1"
1(
#480000
0"
0(
#485000
1"
1(
#490000
0"
0(
#495000
1"
1(
#500000
0"
0(
#505000
1"
1(
#510000
0"
0(
#515000
1"
1(
#520000
0"
0(
#525000
1"
1(
#530000
0"
0(
#535000
1"
1(
#540000
0"
0(
#545000
1"
1(
#550000
0"
0(
#555000
1"
1(
#560000
0"
0(
#565000
1"
1(
#570000
0"
0(
#575000
1"
1(
#580000
0"
0(
#585000
1"
1(
#590000
0"
0(
#595000
1"
1(
#600000
0"
0(
#605000
1"
1(
#610000
0"
0(
#615000
1"
1(
#620000
0"
0(
#625000
1"
1(
#630000
0"
0(
#635000
1"
1(
#640000
0"
0(
#645000
1"
1(
#650000
0"
0(
#655000
1"
1(
#660000
0"
0(
#665000
1"
1(
#670000
0"
0(
#675000
1"
1(
#680000
0"
0(
#685000
1"
1(
#690000
0"
0(
#695000
1"
1(
#700000
0"
0(
#705000
1"
1(
#710000
0"
0(
#715000
1"
1(
#720000
0"
0(
#725000
1"
1(
#730000
0"
0(
#735000
1"
1(
#740000
0"
0(
#745000
1"
1(
#750000
0"
0(
#755000
1"
1(
#760000
0"
0(
#765000
1"
1(
#770000
0"
0(
#775000
1"
1(
#780000
0"
0(
#785000
1"
1(
#790000
0"
0(
#795000
1"
1(
#800000
0"
0(
#805000
1"
1(
#810000
0"
0(
#815000
1"
1(
#820000
0"
0(
#825000
1"
1(
#830000
0"
0(
#835000
1"
1(
#840000
0"
0(
#845000
1"
1(
#850000
0"
0(
#855000
1"
1(
#860000
0"
0(
#865000
1"
1(
#870000
0"
0(
#875000
1"
1(
#880000
0"
0(
#885000
1"
1(
#890000
0"
0(
#895000
1"
1(
#900000
0"
0(
#905000
1"
1(
#910000
0"
0(
#915000
1"
1(
#920000
0"
0(
#925000
1"
1(
#930000
0"
0(
#935000
1"
1(
#940000
0"
0(
#945000
1"
1(
#950000
0"
0(
#955000
1"
1(
#960000
0"
0(
#965000
1"
1(
#970000
0"
0(
#975000
1"
1(
#980000
0"
0(
#985000
1"
1(
#990000
0"
0(
#995000
1"
1(
#1000000
1!
0"
0(
1'
#1005000
1"
1(
#1010000
0"
0(
#1015000
1"
1(
#1020000
0"
0(
#1025000
1"
1(
#1030000
0"
0(
#1035000
1"
1(
#1040000
0"
0(
#1045000
1"
1(
#1050000
0"
0(
#1055000
1"
1(
#1060000
0"
0(
#1065000
1"
1(
#1070000
0"
0(
#1075000
1"
1(
#1080000
0"
0(
#1085000
1"
1(
#1090000
0"
0(
#1095000
1"
1(
#1100000
0"
0(
#1105000
1"
1(
#1110000
0"
0(
#1115000
1"
1(
#1120000
0"
0(
#1125000
1"
1(
#1130000
0"
0(
#1135000
1"
1(
#1140000
0"
0(
#1145000
1"
1(
#1150000
0"
0(
#1155000
1"
1(
#1160000
0"
0(
#1165000
1"
1(
#1170000
0"
0(
#1175000
1"
1(
#1180000
0"
0(
#1185000
1"
1(
#1190000
0"
0(
#1195000
1"
1(
#1200000
1#
0"
0(
1)
#1205000
1"
1(
1+
1%
#1210000
0"
0(
#1215000
1"
1(
#1220000
0"
0(
#1225000
1"
1(
#1230000
0"
0(
#1235000
1"
1(
#1240000
0"
0(
#1245000
1"
1(
#1250000
0"
0(
#1255000
1"
1(
#1260000
0"
0(
#1265000
1"
1(
#1270000
0"
0(
#1275000
1"
1(
#1280000
0"
0(
#1285000
1"
1(
#1290000
0"
0(
#1295000
1"
1(
#1300000
b1010 $
0"
0(
b1010 *
#1305000
1"
1(
b1010 ,
b1010 &
#1310000
0"
0(
#1315000
1"
1(
#1320000
0"
0(
#1325000
1"
1(
#1330000
0"
0(
#1335000
1"
1(
#1340000
0"
0(
#1345000
1"
1(
#1350000
0"
0(
#1355000
1"
1(
#1360000
0"
0(
#1365000
1"
1(
#1370000
0"
0(
#1375000
1"
1(
#1380000
0"
0(
#1385000
1"
1(
#1390000
0"
0(
#1395000
1"
1(
#1400000
0"
0(
#1405000
1"
1(
#1410000
0"
0(
#1415000
1"
1(
#1420000
0"
0(
#1425000
1"
1(
#1430000
0"
0(
#1435000
1"
1(
#1440000
0"
0(
#1445000
1"
1(
#1450000
0"
0(
#1455000
1"
1(
#1460000
0"
0(
#1465000
1"
1(
#1470000
0"
0(
#1475000
1"
1(
#1480000
0"
0(
#1485000
1"
1(
#1490000
0"
0(
#1495000
1"
1(
#1500000
0"
0(
#1505000
1"
1(
#1510000
0"
0(
#1515000
1"
1(
#1520000
0"
0(
#1525000
1"
1(
#1530000
0"
0(
#1535000
1"
1(
#1540000
0"
0(
#1545000
1"
1(
#1550000
0"
0(
#1555000
1"
1(
#1560000
0"
0(
#1565000
1"
1(
#1570000
0"
0(
#1575000
1"
1(
#1580000
0"
0(
#1585000
1"
1(
#1590000
0"
0(
#1595000
1"
1(
#1600000
0"
0(
#1605000
1"
1(
#1610000
0"
0(
#1615000
1"
1(
#1620000
0"
0(
#1625000
1"
1(
#1630000
0"
0(
#1635000
1"
1(
#1640000
0"
0(
#1645000
1"
1(
#1650000
0"
0(
#1655000
1"
1(
#1660000
0"
0(
#1665000
1"
1(
#1670000
0"
0(
#1675000
1"
1(
#1680000
0"
0(
#1685000
1"
1(
#1690000
0"
0(
#1695000
1"
1(
#1700000
0"
0(
#1705000
1"
1(
#1710000
0"
0(
#1715000
1"
1(
#1720000
0"
0(
#1725000
1"
1(
#1730000
0"
0(
#1735000
1"
1(
#1740000
0"
0(
#1745000
1"
1(
#1750000
0"
0(
#1755000
1"
1(
#1760000
0"
0(
#1765000
1"
1(
#1770000
0"
0(
#1775000
1"
1(
#1780000
0"
0(
#1785000
1"
1(
#1790000
0"
0(
#1795000
1"
1(
#1800000
0!
0"
0(
0'
0+
b0 ,
b0 &
0%
#1805000
1"
1(
#1810000
0"
0(
#1815000
1"
1(
#1820000
0"
0(
#1825000
1"
1(
#1830000
0"
0(
#1835000
1"
1(
#1840000
0"
0(
#1845000
1"
1(
#1850000
0"
0(
#1855000
1"
1(
#1860000
0"
0(
#1865000
1"
1(
#1870000
0"
0(
#1875000
1"
1(
#1880000
0"
0(
#1885000
1"
1(
#1890000
0"
0(
#1895000
1"
1(
#1900000
0"
0(
#1905000
1"
1(
#1910000
0"
0(
#1915000
1"
1(
#1920000
0"
0(
#1925000
1"
1(
#1930000
0"
0(
#1935000
1"
1(
#1940000
0"
0(
#1945000
1"
1(
#1950000
0"
0(
#1955000
1"
1(
#1960000
0"
0(
#1965000
1"
1(
#1970000
0"
0(
#1975000
1"
1(
#1980000
0"
0(
#1985000
1"
1(
#1990000
0"
0(
#1995000
1"
1(
#2000000
0#
b0 $
0"
0(
b0 *
0)
#2005000
1"
1(
#2010000
0"
0(
#2015000
1"
1(
#2020000
0"
0(
#2025000
1"
1(
#2030000
0"
0(
#2035000
1"
1(
#2040000
0"
0(
#2045000
1"
1(
#2050000
0"
0(
#2055000
1"
1(
#2060000
0"
0(
#2065000
1"
1(
#2070000
0"
0(
#2075000
1"
1(
#2080000
0"
0(
#2085000
1"
1(
#2090000
0"
0(
#2095000
1"
1(
#2100000
0"
0(
#2105000
1"
1(
#2110000
0"
0(
#2115000
1"
1(
#2120000
0"
0(
#2125000
1"
1(
#2130000
0"
0(
#2135000
1"
1(
#2140000
0"
0(
#2145000
1"
1(
#2150000
0"
0(
#2155000
1"
1(
#2160000
0"
0(
#2165000
1"
1(
#2170000
0"
0(
#2175000
1"
1(
#2180000
0"
0(
#2185000
1"
1(
#2190000
0"
0(
#2195000
1"
1(
#2200000
0"
0(
#2205000
1"
1(
#2210000
0"
0(
#2215000
1"
1(
#2220000
0"
0(
#2225000
1"
1(
#2230000
0"
0(
#2235000
1"
1(
#2240000
0"
0(
#2245000
1"
1(
#2250000
0"
0(
#2255000
1"
1(
#2260000
0"
0(
#2265000
1"
1(
#2270000
0"
0(
#2275000
1"
1(
#2280000
0"
0(
#2285000
1"
1(
#2290000
0"
0(
#2295000
1"
1(
#2300000
1#
b1111 $
0"
0(
b1111 *
1)
#2305000
1"
1(
#2310000
0"
0(
#2315000
1"
1(
#2320000
0"
0(
#2325000
1"
1(
#2330000
0"
0(
#2335000
1"
1(
#2340000
0"
0(
#2345000
1"
1(
#2350000
0"
0(
#2355000
1"
1(
#2360000
0"
0(
#2365000
1"
1(
#2370000
0"
0(
#2375000
1"
1(
#2380000
0"
0(
#2385000
1"
1(
#2390000
0"
0(
#2395000
1"
1(
#2400000
1!
0"
0(
1'
#2405000
1"
1(
b1111 ,
1+
1%
b1111 &
